pbix_to_mcp/__init__.py
pbix_to_mcp/cli.py
pbix_to_mcp/core.py
pbix_to_mcp/extractors/__init__.py
pbix_to_mcp/extractors/data_extractor.py
pbix_to_mcp/extractors/dax_extractor.py
pbix_to_mcp/extractors/ui_extractor.py
pbix_to_mcp/generators/__init__.py
pbix_to_mcp/generators/mcp_config_generator.py
pbix_to_mcp/generators/sqlite_generator.py
pbix_to_mcp/utils/__init__.py
pbix_to_mcp/utils/file_manager.py
pbix_to_mcp/utils/logger.py
pbix_to_mcp-0.1.0.dist-info/licenses/LICENSE
pbix_to_mcp-0.1.0.dist-info/METADATA
pbix_to_mcp-0.1.0.dist-info/WHEEL
pbix_to_mcp-0.1.0.dist-info/entry_points.txt
pbix_to_mcp-0.1.0.dist-info/top_level.txt
pbix_to_mcp-0.1.0.dist-info/RECORD
