Metadata-Version: 2.4
Name: pbix-to-mcp
Version: 0.1.0
Summary: Convert Power BI (.pbix) files to Model Context Protocol (MCP) servers using Google's genai-toolbox
Author: Generated by GenAI Toolbox
License: MIT
Project-URL: Homepage, https://github.com/gavinHuang/pbix-to-mcp
Project-URL: Repository, https://github.com/gavinHuang/pbix-to-mcp
Project-URL: Issues, https://github.com/gavinHuang/pbix-to-mcp/issues
Keywords: powerbi,mcp,genai-toolbox,business-intelligence,data-analysis
Classifier: Development Status :: 4 - Beta
Classifier: Intended Audience :: Developers
Classifier: Intended Audience :: Information Technology
Classifier: License :: OSI Approved :: MIT License
Classifier: Programming Language :: Python :: 3
Classifier: Programming Language :: Python :: 3.10
Classifier: Programming Language :: Python :: 3.11
Classifier: Programming Language :: Python :: 3.12
Classifier: Topic :: Database
Classifier: Topic :: Office/Business
Classifier: Topic :: Software Development :: Libraries :: Python Modules
Requires-Python: >=3.10
License-File: LICENSE
Requires-Dist: pbixray>=0.3.3
Requires-Dist: pandas>=1.5.0
Requires-Dist: pyyaml>=6.0
Provides-Extra: dev
Requires-Dist: pytest>=7.0.0; extra == "dev"
Requires-Dist: pytest-cov>=4.0.0; extra == "dev"
Requires-Dist: black>=23.0.0; extra == "dev"
Requires-Dist: isort>=5.12.0; extra == "dev"
Requires-Dist: flake8>=6.0.0; extra == "dev"
Requires-Dist: mypy>=1.0.0; extra == "dev"
Dynamic: license-file
